asyncdl/__init__.py
asyncdl/asyncdl.py
asyncdl-0.1.0.dist-info/WHEEL
asyncdl-0.1.0.dist-info/METADATA
asyncdl-0.1.0.dist-info/RECORD
