Metadata-Version: 2.1
Name: asyncdl
Version: 0.1.0
Summary: asyncdl is a simple wrapper around the aiohttp Python library. Its aim is to simplify the process of securely downloading files in Python applications.
License: MIT
Author: Makoto
Author-email: makoto+github@taiga.sh
Requires-Python: >=3.6,<4.0
Classifier: License :: OSI Approved :: MIT License
Classifier: Programming Language :: Python :: 3
Classifier: Programming Language :: Python :: 3.10
Classifier: Programming Language :: Python :: 3.6
Classifier: Programming Language :: Python :: 3.7
Classifier: Programming Language :: Python :: 3.8
Classifier: Programming Language :: Python :: 3.9
Requires-Dist: aiodns (>=3.0.0,<4.0.0)
Requires-Dist: aiohttp (>=3.7.4,<4.0.0)
